jovialengine/__init__.py
jovialengine/animsprite.py
jovialengine/config.py
jovialengine/display.py
jovialengine/fontwrap.py
jovialengine/game.py
jovialengine/gamebuilder.py
jovialengine/gameinput.py
jovialengine/gamesprite.py
jovialengine/inputframe.py
jovialengine/load.py
jovialengine/modebase.py
jovialengine/modegamemenu.py
jovialengine/offsetgroup.py
jovialengine/save.py
jovialengine/saveable.py
jovialengine/utility.py
jovialengine-0.27.3.dist-info/licenses/LICENSE.txt
jovialengine-0.27.3.dist-info/METADATA
jovialengine-0.27.3.dist-info/WHEEL
jovialengine-0.27.3.dist-info/top_level.txt
jovialengine-0.27.3.dist-info/RECORD
