Metadata-Version: 2.4
Name: jovialengine
Version: 0.27.3
Summary: A Simple Pygame-ce Engine
Home-page: https://github.com/JovialKnoll/jovialengine
Author: Brett Kaplan
Author-email: BrettCKaplan@gmail.com
License: MIT
Project-URL: Source, https://github.com/JovialKnoll/jovialengine
Project-URL: Issue Tracker, https://github.com/JovialKnoll/jovialengine/issues
Classifier: Programming Language :: Python :: 3
Classifier: Operating System :: OS Independent
Classifier: Intended Audience :: Developers
Requires-Python: >=3.11
License-File: LICENSE.txt
Requires-Dist: pygame-ce>=2.5
Dynamic: license-file
Dynamic: requires-dist
